{"stem":"1799","instances":[{"docId":"Lektuereliste","docUri":"Lektuereliste.html","score":5,"contexts":[{"form":"1799","weight":"1","pos":6046,"context":"...Heldengedicht in drei Theilen. Drei Bände.. Dortmund <mark>1799<\/mark>. [1. Teil anonym Münster 1784] →Jugend...","fid":"page"},{"form":"1799","weight":"1","pos":6825,"context":"...287] Lichtenberg Georg Christoph (1. 7. 1742 – 24. 2. <mark>1799<\/mark>) → Tagebuch → bahrschnitzler","fid":"page"},{"form":"1799","weight":"1","pos":11636,"context":"...Beaumarchais Pierre Augustin Caron de (24. 1. 1732 – 18. 5. <mark>1799<\/mark>) → Tagebuch → bahrschnitzler","fid":"page"},{"form":"1799","weight":"1","pos":14806,"context":"...Jeanneton de la place Maubert. Paris 1798–<mark>1799<\/mark>. ","fid":"page"},{"form":"1799","weight":"1","pos":22778,"context":"[R26] Puškin Aleksandr Sergeevič (6. 6. <mark>1799<\/mark> – 10. 2. 1837)","fid":"page"}]}]}