{"stem":"1825","instances":[{"docId":"Lektuereliste","docUri":"Lektuereliste.html","score":3,"contexts":[{"form":"1825","weight":"1","pos":6342,"context":"[D273] Ferdinand Lassalle (<mark>1825<\/mark> – 1864) → Tagebuch","fid":"page"},{"form":"1825","weight":"1","pos":16341,"context":"...[Conte Alessandro Manzoni: I promessi sposi. <mark>1825<\/mark>–1826.] ","fid":"page"},{"form":"1825","weight":"1","pos":18061,"context":"...1880. [Thomas Babington Macaulay: Milton. <mark>1825<\/mark>.] ","fid":"page"}]}]}