{"stem":"1856","instances":[{"docId":"Lektuereliste","docUri":"Lektuereliste.html","score":19,"contexts":[{"form":"1856","weight":"1","pos":583,"context":" Berthold Auerbach: Barfüßele. Stuttgart, Augsburg <mark>1856<\/mark>. ","fid":"page"},{"form":"1856","weight":"1","pos":3593,"context":"...Sträflinge. Australischer Roman. Drei Bände.. Leipzig <mark>1856<\/mark>. ","fid":"page"},{"form":"1856","weight":"1","pos":3869,"context":"...Grimm: Die Sängerin. In: Novellen. Berlin <mark>1856<\/mark>. ","fid":"page"},{"form":"1856","weight":"1","pos":3875,"context":"...Herman Grimm: Cajetan. In: Novellen. Berlin <mark>1856<\/mark>. ","fid":"page"},{"form":"1856","weight":"1","pos":3881,"context":"...Grimm: Das Kind. In: Novellen. Berlin <mark>1856<\/mark>. ","fid":"page"},{"form":"1856","weight":"1","pos":3887,"context":"...Grimm: Das Abenteuer. In: Novellen. Berlin <mark>1856<\/mark>. ","fid":"page"},{"form":"1856","weight":"1","pos":4134,"context":"...von Hackländer: Erlebtes. Zwei Bände.. Stuttgart <mark>1856<\/mark>. ","fid":"page"},{"form":"1856","weight":"1","pos":4495,"context":"[D193] Heinrich Heine (1797 – <mark>1856<\/mark>) → Tagebuch","fid":"page"},{"form":"1856","weight":"1","pos":7445,"context":"...Reise nach Prag. Novelle. Stuttgart, Augsburg <mark>1856<\/mark>. ","fid":"page"},{"form":"1856","weight":"1","pos":9072,"context":"...[D395] [?] Robert Schumann (1810 – <mark>1856<\/mark>) → Tagebuch","fid":"page"},{"form":"1856","weight":"1","pos":10990,"context":"...[Edmond About: Les mariages de Paris. <mark>1856<\/mark>.] ","fid":"page"},{"form":"1856","weight":"1","pos":12555,"context":"...: Madame Bovary. Mœurs de province. Paris <mark>1856<\/mark>. → Tagebuch →Briefe 1875–1912 ","fid":"page"},{"form":"1856","weight":"1","pos":12794,"context":"...: Avatar. In: Le moniteur universel. Paris <mark>1856<\/mark>. ","fid":"page"},{"form":"1856","weight":"1","pos":18361,"context":"[GB42] George Bernard Shaw (<mark>1856<\/mark> – 1950) → Tagebuch","fid":"page"},{"form":"1856","weight":"1","pos":18952,"context":"[P4] Adam Mickiewicz (1798 – <mark>1856<\/mark>)","fid":"page"},{"form":"1856","weight":"1","pos":22540,"context":"...[Lev Nikolaevič Graf Tolstoj: Dva gusara. <mark>1856<\/mark>.] ","fid":"page"},{"form":"1856","weight":"1","pos":22657,"context":".... {oder} Lev Nikolaevič Graf Tolstoj: Junost’. <mark>1856<\/mark>.] ","fid":"page"},{"form":"1856","weight":"1","pos":22970,"context":"...Ivan Sergeevič Turgenev: Faust. In: Sovremennik. <mark>1856<\/mark>.] ","fid":"page"},{"form":"1856","weight":"1","pos":23201,"context":"...Ivan Sergeevič Turgenev: Rudin. In: Sovremennik. <mark>1856<\/mark>.] ","fid":"page"}]}]}