{"stem":"1914","instances":[{"docId":"Aurnhammer_Lektuereliste_2_4","docUri":"Aurnhammer_Lektuereliste_2.4.html","score":35,"contexts":[{"form":"1914","weight":"1","pos":1002,"context":"...Berend: Die Bräutigame der Babette Bomberling. Berlin <mark>1914<\/mark>. ","fid":"lange-liste"},{"form":"1914","weight":"1","pos":1132,"context":"...Bermann: Das Seil. Eine Ehegeschichte. Berlin <mark>1914<\/mark>. ","fid":"lange-liste"},{"form":"1914","weight":"1","pos":2553,"context":"...Zeitwende. Ein Schauspiel in fünf Akten. Leipzig <mark>1914<\/mark>. ","fid":"lange-liste"},{"form":"1914","weight":"1","pos":2692,"context":"...: Maréchal Niel und andere dumme Geschichten. Brünn <mark>1914<\/mark>. ","fid":"lange-liste"},{"form":"1914","weight":"1","pos":2888,"context":"...Die Räuberbande. Roman. München, [u. a.] <mark>1914<\/mark>. ","fid":"lange-liste"},{"form":"1914","weight":"1","pos":3202,"context":"...Herman Frobenius: Des Deutschen Reiches Schicksalsstunde. Berlin <mark>1914<\/mark>. [13. Auflage] ","fid":"lange-liste"},{"form":"1914","weight":"1","pos":3469,"context":"...August Greeven: Casanova. Drei Szenen. Berlin <mark>1914<\/mark>. ","fid":"lange-liste"},{"form":"1914","weight":"1","pos":4550,"context":"...Arthur Holitscher: Geschichten aus zwei Welten. Berlin <mark>1914<\/mark>. ","fid":"lange-liste"},{"form":"1914","weight":"1","pos":4715,"context":"...in Deutschland. Drei Bände.. Leipzig 1912–<mark>1914<\/mark>. ","fid":"lange-liste"},{"form":"1914","weight":"1","pos":5004,"context":"...von Calais. Bühnenspiel in drei Akten. Berlin <mark>1914<\/mark>. ","fid":"lange-liste"},{"form":"1914","weight":"1","pos":5645,"context":"...Langer: Das böse Schicksal. München, Leipzig <mark>1914<\/mark>. ","fid":"lange-liste"},{"form":"1914","weight":"1","pos":5809,"context":".... Mit vier Essais. Halle an der Saale <mark>1914<\/mark>. ","fid":"lange-liste"},{"form":"1914","weight":"1","pos":7472,"context":"...der Nacht. Komödie in drei Akten. Wien <mark>1914<\/mark>. ","fid":"lange-liste"},{"form":"1914","weight":"1","pos":8399,"context":" Carl Spitteler: Meine frühesten Erlebnisse.. Jena <mark>1914<\/mark>. ","fid":"lange-liste"},{"form":"1914","weight":"1","pos":8562,"context":"...Der Snob. Komödie in drei Aufzügen. Leipzig <mark>1914<\/mark>. ","fid":"lange-liste"},{"form":"1914","weight":"1","pos":8570,"context":"...Bürger Schippel. Komödie in fünf Aufzügen. Leipzig <mark>1914<\/mark>. ","fid":"lange-liste"},{"form":"1914","weight":"1","pos":8816,"context":"...Erbe. Eine Tragödie in drei Aufzügen. Berlin <mark>1914<\/mark>. ","fid":"lange-liste"},{"form":"1914","weight":"1","pos":9041,"context":"...1852).Herausgegeben von René van Rhyn. München <mark>1914<\/mark>. ","fid":"lange-liste"},{"form":"1914","weight":"1","pos":9096,"context":"...Mathilde Vaerting: Das Recht des Kindes?. Leipzig <mark>1914<\/mark>. ","fid":"lange-liste"},{"form":"1914","weight":"1","pos":9401,"context":"...Brand der Leidenschaften. Novelle. Wien, Leipzig <mark>1914<\/mark>. ","fid":"lange-liste"},{"form":"1914","weight":"1","pos":9470,"context":"...Anton Wildgans: Armut. Ein Trauerspiel. Leipzig <mark>1914<\/mark>. ","fid":"lange-liste"},{"form":"1914","weight":"1","pos":9546,"context":"...Wittels: Der Juwelier von Bagdad. Roman. <mark>1914<\/mark>. ","fid":"lange-liste"},{"form":"1914","weight":"1","pos":9778,"context":" Arnold Zweig: Ritualmord in Ungarn. Berlin <mark>1914<\/mark>. ","fid":"lange-liste"},{"form":"1914","weight":"1","pos":10318,"context":"...Übersetzt von J. Frankenberger, W. Fränzel. Jena <mark>1914<\/mark>. [Henri Bergson: Le rire. Essai...","fid":"lange-liste"},{"form":"1914","weight":"1","pos":10372,"context":" Tristan Bernard: Jeanne Doré. Paris <mark>1914<\/mark>. ","fid":"lange-liste"},{"form":"1914","weight":"1","pos":10381,"context":"...: Lebenserinnerungen. Übersetzt von H. Scholz. München <mark>1914<\/mark>. [Hector Berlioz: Mémoires. 1870.]...","fid":"lange-liste"},{"form":"1914","weight":"1","pos":12158,"context":" Henri Lavedan: Les grandes heures. <mark>1914<\/mark>–1915. Paris 1915. ","fid":"lange-liste"},{"form":"1914","weight":"1","pos":13502,"context":"...von E. und O. Grautoff. Frankfurt am Main <mark>1914<\/mark>–1917. [Romain Rolland: Jean-...","fid":"lange-liste"},{"form":"1914","weight":"1","pos":14081,"context":" Fernand Vanderem: La victime. Paris <mark>1914<\/mark>. ","fid":"lange-liste"},{"form":"1914","weight":"1","pos":16055,"context":"...Chesterton: Magie. [Ohne Übersetzerangabe.] Ohne Ort <mark>1914<\/mark>. [vermutlich] [Gilbert Keith Chesterton:...","fid":"lange-liste"},{"form":"1914","weight":"1","pos":17264,"context":"...Brand der Leidenschaften. Novelle. Wien, Leipzig <mark>1914<\/mark>. ","fid":"lange-liste"},{"form":"1914","weight":"1","pos":18583,"context":"...letzte Freude. Übersetzt von N. Hoyer. München <mark>1914<\/mark>. [Knut Hamsun: Den sidste Glæde....","fid":"lange-liste"},{"form":"1914","weight":"1","pos":18595,"context":"...Kinder ihrer Zeit. Übersetzt von N. Hoyer. München <mark>1914<\/mark>. [Knut Hamsun: Børn av tiden....","fid":"lange-liste"},{"form":"1914","weight":"1","pos":19860,"context":"...Geschichte. Übersetzt von E. K. Rahsin. München <mark>1914<\/mark>. [Fëdor Michajlovič Dostoevskij: Skvernyj anekdot....","fid":"lange-liste"},{"form":"1914","weight":"1","pos":19895,"context":"...: Briefe. Übersetzt von A. Eliasberg. München <mark>1914<\/mark>. [oder] Fëdor Michajlovič Dostoevskij: Briefe. Übersetzt...","fid":"lange-liste"}]}]}