{"stem":"alphons","instances":[{"docId":"Lektuereliste","docUri":"Lektuereliste.html","score":17,"contexts":[{"form":"Alphonse","weight":"1","pos":12183,"context":" <mark>Alphonse<\/mark> Daudet: Jack. Mœurs contemporaines. Paris 1875...","fid":"page"},{"form":"Alphonse","weight":"1","pos":12190,"context":" <mark>Alphonse<\/mark> Daudet: Fromont jeune et Risler aîné. Mœurs...","fid":"page"},{"form":"Alphonse","weight":"1","pos":12203,"context":" <mark>Alphonse<\/mark> Daudet: Les aventures prodigieuses de Tartarin de Tarascon...","fid":"page"},{"form":"Alphonse","weight":"1","pos":12212,"context":" <mark>Alphonse<\/mark> Daudet: Der kleine Dingsda, Geschichte eines Kindes...","fid":"page"},{"form":"Alphonse","weight":"1","pos":12220,"context":"...Kindes. [Ohne Übersetzerangabe.] Berlin 1877. [<mark>Alphonse<\/mark> Daudet: Le petit chose. Histoire d’un enfant...","fid":"page"},{"form":"Alphonse","weight":"1","pos":12228,"context":" <mark>Alphonse<\/mark> Daudet: Künstler-Ehen. Pariser Skizzen....","fid":"page"},{"form":"Alphonse","weight":"1","pos":12239,"context":"...Übersetzt von A. Berstmann. Leipzig 1880. [<mark>Alphonse<\/mark> Daudet: Les femmes d’artistes. 1876.] ","fid":"page"},{"form":"Alphonse","weight":"1","pos":12245,"context":" <mark>Alphonse<\/mark> Daudet: Montagsgeschichten. Übersetzt von S. Born....","fid":"page"},{"form":"Alphonse","weight":"1","pos":12252,"context":"...Übersetzt von S. Born. Basel 1880. [<mark>Alphonse<\/mark> Daudet: Les Contes du Lundi. 1873.]...","fid":"page"},{"form":"Alphonse","weight":"1","pos":12258,"context":" <mark>Alphonse<\/mark> Daudet: Sappho. Pariser Sittenbild. [Ohne Übersetzerangabe...","fid":"page"},{"form":"Alphonse","weight":"1","pos":12269,"context":"...1884. [mit Adolphe Bélot] → Tagebuch [<mark>Alphonse<\/mark> Daudet: Sapho. Mœurs parisiennes. 1884.]...","fid":"page"},{"form":"Alphonse","weight":"1","pos":12275,"context":" <mark>Alphonse<\/mark> Daudet: L’immortel. Mœurs parisiennes. Paris 1888...","fid":"page"},{"form":"Alphonse","weight":"1","pos":12282,"context":" <mark>Alphonse<\/mark> Daudet: Les rois en exil. Roman parisien...","fid":"page"},{"form":"Alphonse","weight":"1","pos":13321,"context":" <mark>Alphonse<\/mark> Karr: Plus ça change et plus c’est la...","fid":"page"},{"form":"Alphonse","weight":"1","pos":13391,"context":" <mark>Alphonse<\/mark>-Marie Louis Prat de Lamartine: Raphaël,...","fid":"page"},{"form":"Alphonse","weight":"1","pos":13404,"context":" <mark>Alphonse<\/mark>-Marie Louis Prat de Lamartine: Souvenirs,...","fid":"page"},{"form":"Alphonse","weight":"1","pos":13424,"context":"...ou Note d’un voyageur. Bruxelles 1835. [oder] <mark>Alphonse<\/mark>-Marie Louis Prat de Lamartine: Souvenirs et...","fid":"page"}]}]}