{"stem":"ambrosius","instances":[{"docId":"Lektuereliste","docUri":"Lektuereliste.html","score":3,"contexts":[{"form":"Ambrosius","weight":"1","pos":20708,"context":" Molbech .... <mark>Ambrosius<\/mark>","fid":"page"},{"form":"Ambrosius","weight":"1","pos":20713,"context":" Christian Knud Frederik Molbech: <mark>Ambrosius<\/mark>. Schauspiel in vier Aufzügen. Übersetzt von A....","fid":"page"},{"form":"Ambrosius","weight":"1","pos":20724,"context":"...Leipzig 1878. [Christian Knud Frederik Molbech: <mark>Ambrosius<\/mark>. Skuespil i fire Akter. 1877.] ","fid":"page"}]}]}