{"stem":"briefwechsel","instances":[{"docId":"Lektuereliste","docUri":"Lektuereliste.html","score":2,"contexts":[{"form":"Briefwechsel","weight":"1","pos":469,"context":"...Schnitzlers Urteil ist wohlwollend-kritisch; vgl. <mark>Briefwechsel<\/mark> in Deutschen Literaturarchiv Marbach, A:Schnitzler, 85.1...","fid":"page"},{"form":"Briefwechsel","weight":"1","pos":1670,"context":"[D255] →M. Kolloden [vgl. <mark>Briefwechsel<\/mark> in Deutschen Literaturarchiv, A:Schnitzler, 85.1....","fid":"page"}]}]}