{"stem":"buckl","instances":[{"docId":"Aurnhammer_Lektuereliste_2_4","docUri":"Aurnhammer_Lektuereliste_2.4.html","score":3,"contexts":[{"form":"Buckle","weight":"1","pos":15886,"context":" <mark>Buckle<\/mark> Engl Civil ","fid":"lange-liste"},{"form":"Buckle","weight":"1","pos":15891,"context":" Thomas Henry <mark>Buckle<\/mark>: Geschichte der Zivilisation in England. Übersetzt von...","fid":"lange-liste"},{"form":"Buckle","weight":"1","pos":15904,"context":"...–1862. [Zwei Bände.] [Thomas Henry <mark>Buckle<\/mark>: History of civilisation in England. 1857–...","fid":"lange-liste"}]}]}