{"stem":"chabert","instances":[{"docId":"Lektuereliste","docUri":"Lektuereliste.html","score":3,"contexts":[{"form":"Chabert","weight":"1","pos":11024,"context":"...\/ Ballsp. Katze \/ Blutrache \/ Mundtot \/ <mark>Chabert<\/mark> \/ Honorine \/ Peau -- Illusion \/ Pysid....","fid":"page"},{"form":"Chabert","weight":"1","pos":11140,"context":" Honoré de Balzac: Oberst <mark>Chabert<\/mark>. Übersetzt von H. Denhardt. Leipzig 1886....","fid":"page"},{"form":"Chabert","weight":"1","pos":11148,"context":"...1886. [Honoré de Balzac: Le colonel <mark>Chabert<\/mark>. 1832.] ","fid":"page"}]}]}