{"stem":"comt","instances":[{"docId":"Aurnhammer_Lektuereliste_2_4","docUri":"Aurnhammer_Lektuereliste_2.4.html","score":7,"contexts":[{"form":"comte","weight":"1","pos":10676,"context":" Victor Charles Cherbuliez: Le <mark>comte<\/mark> Kostia. Paris 1863. ","fid":"lange-liste"},{"form":"Comtes","weight":"1","pos":10863,"context":" Coppeé Henriette .\/.. <mark>Comtes<\/mark> rap. \/ Contes en prose","fid":"lange-liste"},{"form":"comte","weight":"1","pos":11129,"context":"...1846. [Alexandre Dumas, père: Le <mark>comte<\/mark> de Monte-Cristo. 1845–1846.]...","fid":"lange-liste"},{"form":"Comte","weight":"1","pos":11704,"context":" Ferdinand de <mark>Comte<\/mark>: Les mémoires de Frontin. Leipzig 1859....","fid":"lange-liste"},{"form":"Comte","weight":"1","pos":12841,"context":" Xavier-Aymon, <mark>Comte<\/mark> de Montépin: Die Sünderinnen. [Ohne Übersetzerangabe.]...","fid":"lange-liste"},{"form":"Comte","weight":"1","pos":12851,"context":"...1874–1877. [Xavier-Aymon, <mark>Comte<\/mark> de Montépin: Les pécheresses. 1849.] ","fid":"lange-liste"},{"form":"Comte","weight":"1","pos":14259,"context":" Philippe-Auguste, <mark>Comte<\/mark> de Villiers de l’Isle-Adam: Contes cruels...","fid":"lange-liste"}]}]}