{"stem":"edmond","instances":[{"docId":"Lektuereliste","docUri":"Lektuereliste.html","score":11,"contexts":[{"form":"Edmond","weight":"1","pos":10977,"context":" <mark>Edmond<\/mark> About: Pariser Ehen. Übersetzt von D. Duncker...","fid":"page"},{"form":"Edmond","weight":"1","pos":10985,"context":"...Übersetzt von D. Duncker. Stuttgart 1886. [<mark>Edmond<\/mark> About: Les mariages de Paris. 1856.]...","fid":"page"},{"form":"Edmond","weight":"1","pos":10991,"context":" <mark>Edmond<\/mark> About: Der Mann mit dem abgebrochenen Ohr....","fid":"page"},{"form":"Edmond","weight":"1","pos":10999,"context":"...Übersetzt von H. Meerholz. Leipzig 1885. [<mark>Edmond<\/mark> About: L’homme à l’oreille cassée. 1863.]...","fid":"page"},{"form":"Edmond","weight":"1","pos":11005,"context":" <mark>Edmond<\/mark> About: L’Infame. Paris 1867. ","fid":"page"},{"form":"Edmond","weight":"1","pos":12918,"context":" Jules de Goncourt, <mark>Edmond<\/mark> de Goncourt: Renée Mauperin. Paris 1864....","fid":"page"},{"form":"Edmond","weight":"1","pos":12926,"context":" Jules de Goncourt, <mark>Edmond<\/mark> de Goncourt: Germinie Lacerteux. Paris 1864....","fid":"page"},{"form":"Edmond","weight":"1","pos":12934,"context":" Jules de Goncourt, <mark>Edmond<\/mark> de Goncourt: Journal des Goncourt. Mémoires de...","fid":"page"},{"form":"Edmond","weight":"1","pos":12947,"context":" Jules de Goncourt, <mark>Edmond<\/mark> de Goncourt: Chérie. Paris 1884. ","fid":"page"},{"form":"Edmond","weight":"1","pos":12954,"context":" Jules de Goncourt, <mark>Edmond<\/mark> de Goncourt: La fille Élisa. Paris 1877...","fid":"page"},{"form":"Edmond","weight":"1","pos":12962,"context":" Jules de Goncourt, <mark>Edmond<\/mark> de Goncourt: Manette Salomon. Paris 1867....","fid":"page"}]}]}