{"stem":"elisabeth","instances":[{"docId":"Lektuereliste","docUri":"Lektuereliste.html","score":6,"contexts":[{"form":"Elisabeth","weight":"1","pos":830,"context":" Rudolf Hans Bartsch: <mark>Elisabeth<\/mark> Kött. Roman. Leipzig 1909. → Tagebuch...","fid":"page"},{"form":"Elisabeth","weight":"1","pos":6062,"context":" Kory Towska[?] , Kory <mark>Elisabeth<\/mark> Rosenbaum[?] : Die Hosen des Herrn von Bredow...","fid":"page"},{"form":"Elisabeth","weight":"1","pos":10659,"context":" <mark>Elisabeth<\/mark> Werner: Ein Held der Feder. Leipzig 1871...","fid":"page"},{"form":"Elisabeth","weight":"1","pos":21605,"context":"...von E. K. Rahsin. München 1909. [<mark>Elisabeth<\/mark> Kaerrick] [Fëdor Michajlovič Dostoevskij: Prestuplenie i...","fid":"page"},{"form":"Elisabeth","weight":"1","pos":21907,"context":"...von E. K. Rahsin. Leipzig 1918. [<mark>Elisabeth<\/mark> Kaerrick] [Fëdor Michajlovič Dostoevskij: Chozjajka....","fid":"page"},{"form":"Elisabeth","weight":"1","pos":21973,"context":"...Rahsin. München, u. a. 1906. [=<mark>Elisabeth<\/mark> Kaerrick] [Fëdor Michajlovič Dostoevskij: Besy....","fid":"page"}]}]}