{"stem":"eller","instances":[{"docId":"Aurnhammer_Lektuereliste_2_4","docUri":"Aurnhammer_Lektuereliste_2.4.html","score":2,"contexts":[{"form":"Eller","weight":"1","pos":19026,"context":"...1882. [Jonas Lie: Den Fremsynte. <mark>Eller<\/mark> billeder fra Nordland. 1870.] ","fid":"lange-liste"},{"form":"eller","weight":"1","pos":19355,"context":"...Amsterdam 1808. [Adam Gottlob Oehlenschläger: Aladdin <mark>eller<\/mark> den forunderlige lampe. Dramatisk eventyr. 1805.]...","fid":"lange-liste"}]}]}