{"stem":"erb","instances":[{"docId":"Aurnhammer_Lektuereliste_2_4","docUri":"Aurnhammer_Lektuereliste_2.4.html","score":3,"contexts":[{"form":"Erbe","weight":"1","pos":4657,"context":" Hans von Hopfen: Der Genius und sein <mark>Erbe<\/mark>. Eine Künstlergeschichte. Stuttgart 1887. ","fid":"lange-liste"},{"form":"Erbe","weight":"1","pos":8812,"context":"...Terramare, Georg Eisler von Terramare: Des Odysseus <mark>Erbe<\/mark>. Eine Tragödie in drei Aufzügen. Berlin 1914...","fid":"lange-liste"},{"form":"Erbe","weight":"1","pos":10573,"context":" Chavette .... <mark>Erbe<\/mark> des Schmarotzers \/ Lilly \/","fid":"lange-liste"}]}]}