{"stem":"feuerbach","instances":[{"docId":"Lektuereliste","docUri":"Lektuereliste.html","score":3,"contexts":[{"form":"Feuerbach","weight":"1","pos":2888,"context":" <mark>Feuerbach<\/mark> --- Vermächtnis \/","fid":"page"},{"form":"Feuerbach","weight":"1","pos":2892,"context":" Anselm <mark>Feuerbach<\/mark>: Ein Vermächtnis.Herausgegeben von Henriette Feuerbach....","fid":"page"},{"form":"Feuerbach","weight":"1","pos":2896,"context":"...Anselm Feuerbach: Ein Vermächtnis.Herausgegeben von Henriette <mark>Feuerbach<\/mark>. Berlin 1878. ","fid":"page"}]}]}