{"stem":"gazeta","instances":[{"docId":"Aurnhammer_Lektuereliste_2_4","docUri":"Aurnhammer_Lektuereliste_2.4.html","score":3,"contexts":[{"form":"gazeta","weight":"1","pos":20328,"context":"...Aleksej Maksimovič Peškov: Skuki radi. In: Samarskaja <mark>gazeta<\/mark>. 1897. {oder} [?] Maksim Gor’kij, Aleksej...","fid":"lange-liste"},{"form":"gazeta","weight":"1","pos":21020,"context":"...Anton Pavlovič Čechov: V potëmkach. In: Peterburgskaja <mark>gazeta<\/mark>. 1886.] ","fid":"lange-liste"},{"form":"gazeta","weight":"1","pos":21043,"context":"...Scena-monolog v odnom dejstvii. In: Peterburgskaja <mark>gazeta<\/mark>. 1886.] ","fid":"lange-liste"}]}]}