{"stem":"gustav","instances":[{"docId":"Deutschsprachige-Literatur","docUri":"Deutschsprachige-Literatur.html","score":12,"contexts":[{"form":"Gustav","weight":"1","pos":292,"context":"[D43] →<mark>Gustav<\/mark> Biberich","fid":"pmb14191"},{"form":"Gustav","weight":"1","pos":718,"context":"[D116] →<mark>Gustav<\/mark> Fock","fid":"pmb64807"},{"form":"Gustav","weight":"1","pos":765,"context":"[D122] →<mark>Gustav<\/mark> Freytag","fid":"pmb11377"},{"form":"Gustav","weight":"1","pos":818,"context":"[D128] →<mark>Gustav<\/mark> Frenssen","fid":"pmb11367"},{"form":"Gustav","weight":"1","pos":1065,"context":"[D173] →<mark>Gustav<\/mark> Gugitz","fid":"pmb11541"},{"form":"Gustave","weight":"1","pos":1101,"context":"[D177] →Ida Marie Louise Friederike <mark>Gustave<\/mark> Gräfin von Hahn-Hahn","fid":"pmb64822"},{"form":"Gustav","weight":"1","pos":1483,"context":"[D234] →<mark>Gustav<\/mark> Karpeles","fid":"pmb8115"},{"form":"Gustav","weight":"1","pos":1716,"context":"[D270] →<mark>Gustav<\/mark> Landauer","fid":"pmb12031"},{"form":"Gustav","weight":"1","pos":1886,"context":"[D296] →<mark>Gustav<\/mark> Macasy","fid":"pmb64856"},{"form":"Gustav","weight":"1","pos":2029,"context":"[D314] →<mark>Gustav<\/mark> Meyrink","fid":"pmb12248"},{"form":"Gustav","weight":"1","pos":2423,"context":"[D375] →<mark>Gustav<\/mark> Sack","fid":"pmb64883"},{"form":"Gustav","weight":"1","pos":2584,"context":"[D400] →<mark>Gustav<\/mark> Schröer","fid":"pmb64890"}]},{"docId":"Frankreich","docUri":"Frankreich.html","score":3,"contexts":[{"form":"Gustave","weight":"1","pos":296,"context":"[F41] →<mark>Gustave<\/mark> Droz","fid":"pmb64940"},{"form":"Gustave","weight":"1","pos":359,"context":"[F50] →<mark>Gustave<\/mark> Flaubert","fid":"pmb11330"},{"form":"Gustave","weight":"1","pos":1214,"context":"<mark>Gustave<\/mark> Ricouard","fid":"pmb65004"}]},{"docId":"Norden","docUri":"Norden.html","score":1,"contexts":[{"form":"Gustav","weight":"1","pos":93,"context":"[N14] →<mark>Gustav<\/mark> Frederik Esmann","fid":"pmb65068"}]}]}