{"stem":"herman","instances":[{"docId":"Lektuereliste","docUri":"Lektuereliste.html","score":28,"contexts":[{"form":"Herman","weight":"1","pos":3481,"context":" <mark>Herman<\/mark> Frobenius: Des Deutschen Reiches Schicksalsstunde. Berlin 1914...","fid":"page"},{"form":"Herman","weight":"1","pos":3623,"context":" Hermann von Gilm zu Rosenegg: <mark>Herman<\/mark> von Gilms Familien- und Freundesbriefe.Herausgegeben von...","fid":"page"},{"form":"Herman","weight":"1","pos":3864,"context":" <mark>Herman<\/mark> Grimm: Die Sängerin. In: Novellen. Berlin...","fid":"page"},{"form":"Herman","weight":"1","pos":3870,"context":" [?] <mark>Herman<\/mark> Grimm: Cajetan. In: Novellen. Berlin 1856...","fid":"page"},{"form":"Herman","weight":"1","pos":3876,"context":" <mark>Herman<\/mark> Grimm: Das Kind. In: Novellen. Berlin...","fid":"page"},{"form":"Herman","weight":"1","pos":3882,"context":" <mark>Herman<\/mark> Grimm: Das Abenteuer. In: Novellen. Berlin...","fid":"page"},{"form":"Herman","weight":"1","pos":3888,"context":" <mark>Herman<\/mark> Grimm: Goethe. Vorlesungen gehalten an der königlichen...","fid":"page"},{"form":"Herman","weight":"1","pos":3899,"context":" <mark>Herman<\/mark> Grimm: Leben Michelangelo’s. 2 Theile. Hannover...","fid":"page"},{"form":"Herman","weight":"1","pos":19227,"context":" <mark>Herman<\/mark> Bang: Exzentrische Novellen. Berlin 1905. [...","fid":"page"},{"form":"Herman","weight":"1","pos":19233,"context":"...Bang: Exzentrische Novellen. Berlin 1905. [<mark>Herman<\/mark> Bang: Excentriske Noveller. 1885.] ","fid":"page"},{"form":"Herman","weight":"1","pos":19238,"context":" <mark>Herman<\/mark> Bang: Michael. Übersetzt von J. Koppel....","fid":"page"},{"form":"Herman","weight":"1","pos":19246,"context":"...J. Koppel. Berlin 1906. → Tagebuch [<mark>Herman<\/mark> Bang: Mikael. 1904.] ","fid":"page"},{"form":"Herman","weight":"1","pos":19250,"context":" <mark>Herman<\/mark> Bang: Fräulein Caja. Übersetzt von R. Blumenreich...","fid":"page"},{"form":"Herman","weight":"1","pos":19258,"context":"...Übersetzt von R. Blumenreich. München 1897. [<mark>Herman<\/mark> Bang: Frøken Caja. 1912.] ","fid":"page"},{"form":"Herman","weight":"1","pos":19263,"context":" <mark>Herman<\/mark> Bang: Tine. Übersetzt von E. Weise....","fid":"page"},{"form":"Herman","weight":"1","pos":19270,"context":"...Übersetzt von E. Weise. Berlin 1903. [<mark>Herman<\/mark> Bang: Tine. 1889.] ","fid":"page"},{"form":"Herman","weight":"1","pos":19274,"context":" <mark>Herman<\/mark> Bang: Hoffnungslose Geschlechter. Übersetzt von R. Blumenreich...","fid":"page"},{"form":"Herman","weight":"1","pos":19282,"context":"...Übersetzt von R. Blumenreich. Berlin 1900. [<mark>Herman<\/mark> Bang: Haabløse Slægter. 1880.] ","fid":"page"},{"form":"Herman","weight":"1","pos":19287,"context":" <mark>Herman<\/mark> Bang: Am Weg. Übersetzt von E. Jonas....","fid":"page"},{"form":"Herman","weight":"1","pos":19294,"context":"...E. Jonas. Berlin 1898. → Tagebuch [<mark>Herman<\/mark> Bang: Ved vejen. 1886.] ","fid":"page"},{"form":"Herman","weight":"1","pos":19299,"context":" <mark>Herman<\/mark> Bang: Ludwigshöhe. Roman einer Krankenpflegerin. Übersetzt...","fid":"page"},{"form":"Herman","weight":"1","pos":19309,"context":"...M. Franzos. Berlin 1908. → Tagebuch [<mark>Herman<\/mark> Bang: Ludvigshakke. 1896.] ","fid":"page"},{"form":"Herman","weight":"1","pos":19313,"context":" <mark>Herman<\/mark> Bang: Seltsame und andere Geschichten. Übersetzt von...","fid":"page"},{"form":"Herman","weight":"1","pos":19321,"context":"...Übersetzt von J. Koppel. Berlin 1911. [<mark>Herman<\/mark> Bang: Sælsomme Fortællinger.] ","fid":"page"},{"form":"Herman","weight":"1","pos":19325,"context":" <mark>Herman<\/mark> Bang: Zusammenbruch. Übersetzt von H. Klepetar....","fid":"page"},{"form":"Herman","weight":"1","pos":19333,"context":"...H. Klepetar. Berlin 1910. → Tagebuch [<mark>Herman<\/mark> Bang: Stuk. 1912.] ","fid":"page"},{"form":"Herman","weight":"1","pos":20302,"context":" <mark>Herman<\/mark> Heijermans: Ghetto. Übersetzt von Paul Raché....","fid":"page"},{"form":"Herman","weight":"1","pos":20310,"context":"...Übersetzt von Paul Raché. Leipzig 1903. [<mark>Herman<\/mark> Heijermans: Ghetto. 1899.] ","fid":"page"}]}]}