{"stem":"karin","instances":[{"docId":"Lektuereliste","docUri":"Lektuereliste.html","score":4,"contexts":[{"form":"Karin","weight":"1","pos":20909,"context":" <mark>Karin<\/mark> Michaelis: Das Schicksal der Ulla Fangel. Eine...","fid":"page"},{"form":"Karin","weight":"1","pos":20920,"context":".... Übersetzt von M. Mann. Stuttgart 1903. [<mark>Karin<\/mark> Michaelis: Ulla Fangel sorsa. Egy ifjuság megy...","fid":"page"},{"form":"Karin","weight":"1","pos":20932,"context":" <mark>Karin<\/mark> Michaelis: Das gefährliche Alter. Tagebuchaufzeichnungen und Briefe...","fid":"page"},{"form":"Karin","weight":"1","pos":20942,"context":"...von M. Mann. Berlin 1910. → Tagebuch [<mark>Karin<\/mark> Michaelis: Den farlige alder. Breve og Dagbogoptegnelser...","fid":"page"}]}]}