{"stem":"katz","instances":[{"docId":"Lektuereliste","docUri":"Lektuereliste.html","score":3,"contexts":[{"form":"Katze","weight":"1","pos":11021,"context":"...... Femme de trente \/ Paz \/ Ballsp. <mark>Katze<\/mark> \/ Blutrache \/ Mundtot \/ Chabert \/ Honorine \/...","fid":"page"},{"form":"Katze","weight":"1","pos":11083,"context":" Honoré de Balzac: Das Haus zur ballspielenden <mark>Katze<\/mark>. Übersetzt von H. Meerholz. Leipzig 1884....","fid":"page"},{"form":"Katz","weight":"1","pos":16368,"context":"..., Radius[?] : Theresa. Übersetzt von H. <mark>Katz<\/mark>. Leipzig 1898. [ Neera[?] , Anna...","fid":"page"}]}]}