{"stem":"komisch","instances":[{"docId":"Lektuereliste","docUri":"Lektuereliste.html","score":4,"contexts":[{"form":"komisches","weight":"1","pos":5912,"context":" Karl Arnold Kortum: Die Jobsiade. Ein <mark>komisches<\/mark> Heldengedicht in drei Theilen. Drei Bände.. Dortmund...","fid":"page"},{"form":"Komischer","weight":"1","pos":10555,"context":" Adolf von Winterfeld: Der Elephant. <mark>Komischer<\/mark> Roman. Leipzig 1870. ","fid":"page"},{"form":"komisches","weight":"1","pos":10799,"context":"...Justus Friedrich Wilhelm Zachariae: Der Renommiste. Ein <mark>komisches<\/mark> Heldengedicht. In: Belustigung des Verstandes und Witzes,...","fid":"page"},{"form":"komisches","weight":"1","pos":21717,"context":"...Gogol’: Die todten Seelen. Ein satirisch-<mark>komisches<\/mark> Zeitgemälde. Übersetzt von P. Löbenstein. Leipzig 1846...","fid":"page"}]}]}