{"stem":"körner","instances":[{"docId":"Lektuereliste","docUri":"Lektuereliste.html","score":3,"contexts":[{"form":"Körner","weight":"1","pos":6069,"context":" <mark>Körner<\/mark> ","fid":"page"},{"form":"Körner","weight":"1","pos":6070,"context":"   <mark>Körner<\/mark> Theodor (23. 9. 1791 – 26. 8. 1813)   Körner Josef...","fid":"page"},{"form":"Körner","weight":"1","pos":6074,"context":"   Körner Theodor (23. 9. 1791 – 26. 8. 1813)   <mark>Körner<\/mark> Josef (15. 4. 1888 – 9. 5. 1950)   ","fid":"page"}]}]}