{"stem":"l'aventur","instances":[{"docId":"Aurnhammer_Lektuereliste_2_4","docUri":"Aurnhammer_Lektuereliste_2.4.html","score":3,"contexts":[{"form":"L’aventure","weight":"1","pos":10632,"context":" Victor Charles Cherbuliez: <mark>L’aventure<\/mark> de Ladislas Bolski. Paris 1869. ","fid":"lange-liste"},{"form":"L’aventure","weight":"1","pos":14083,"context":" Veber .... <mark>L’aventure<\/mark>","fid":"lange-liste"},{"form":"L’aventure","weight":"1","pos":14086,"context":" Pierre Veber: <mark>L’aventure<\/mark>. Paris 1905. ","fid":"lange-liste"}]}]}