{"stem":"langer","instances":[{"docId":"Aurnhammer_Lektuereliste_2_4","docUri":"Aurnhammer_Lektuereliste_2.4.html","score":4,"contexts":[{"form":"Langer","weight":"1","pos":5627,"context":" <mark>Langer<\/mark> ... Loreley \/ Böse Schicksal \/ Magelone \/ ","fid":"lange-liste"},{"form":"Langer","weight":"1","pos":5633,"context":" Felix <mark>Langer<\/mark>: Lore Ley. München, Leipzig 1913....","fid":"lange-liste"},{"form":"Langer","weight":"1","pos":5640,"context":" Felix <mark>Langer<\/mark>: Das böse Schicksal. München, Leipzig 1914...","fid":"lange-liste"},{"form":"Langer","weight":"1","pos":5647,"context":" Felix <mark>Langer<\/mark>: Magelon. Berlin 1911. ","fid":"lange-liste"}]}]}