{"stem":"laurid","instances":[{"docId":"Aurnhammer_Lektuereliste_2_4","docUri":"Aurnhammer_Lektuereliste_2.4.html","score":4,"contexts":[{"form":"Laurids","weight":"1","pos":18057,"context":" <mark>Laurids<\/mark> Bruun: Pan. Roman in vier Stunden....","fid":"lange-liste"},{"form":"Laurids","weight":"1","pos":18066,"context":"...Übersetzt von J. Koppel. Berlin 1907. [<mark>Laurids<\/mark> Bruun: Pan. Roman i fire timer....","fid":"lange-liste"},{"form":"Laurids","weight":"1","pos":18073,"context":" <mark>Laurids<\/mark> Bruun: Van Zantens glückliche Zeit. Übersetzt von J....","fid":"lange-liste"},{"form":"Laurids","weight":"1","pos":18082,"context":"...Übersetzt von J. Koppel. Berlin 1910. [<mark>Laurids<\/mark> Bruun: Van Zantens lykkelige Tid. 1909.]...","fid":"lange-liste"}]}]}