{"stem":"lesag","instances":[{"docId":"Lektuereliste","docUri":"Lektuereliste.html","score":6,"contexts":[{"form":"Lesage","weight":"1","pos":13801,"context":" <mark>Lesage<\/mark> ..... Hinkender Teufel \/ Diable boit \/ Gil blas...","fid":"page"},{"form":"Lesage","weight":"1","pos":13811,"context":" Alain René <mark>Lesage<\/mark>: Der Hinkende Teufel. Übersetzt von R. A....","fid":"page"},{"form":"Lesage","weight":"1","pos":13821,"context":".... Hamburg 1730. → Tagebuch [Alain René <mark>Lesage<\/mark>: Le diable boiteux. 1707.] ","fid":"page"},{"form":"Lesage","weight":"1","pos":13827,"context":" Alain René <mark>Lesage<\/mark>: Le diable boiteux. Amsterdam 1707. →...","fid":"page"},{"form":"Lesage","weight":"1","pos":13835,"context":" Alain René <mark>Lesage<\/mark>: Der spanische Robinson, oder Sonderbahre Geschichte des...","fid":"page"},{"form":"Lesage","weight":"1","pos":13849,"context":"....] Hamburg 1726. → Tagebuch [Alain René <mark>Lesage<\/mark>: Histoire de Gil Blas de Santillane. 1715...","fid":"page"}]}]}