{"stem":"leut","instances":[{"docId":"Aurnhammer_Lektuereliste_2_4","docUri":"Aurnhammer_Lektuereliste_2.4.html","score":10,"contexts":[{"form":"Leute","weight":"1","pos":2460,"context":" Emil Ertl: Die <mark>Leute<\/mark> vom blauen Guguckshaus. Roman. Leipzig 1906....","fid":"lange-liste"},{"form":"Leute","weight":"1","pos":5866,"context":"...nach d. Westen. \/ Arme Mädchen \/ Wunderliche <mark>Leute<\/mark> \/ Der Abend \/ ","fid":"lange-liste"},{"form":"Leute","weight":"1","pos":5922,"context":" Paul Lindau: Wunderliche <mark>Leute<\/mark>. Kleine Erzählungen. Breslau 1888. ","fid":"lange-liste"},{"form":"Leute","weight":"1","pos":7611,"context":"...des Wand. \/ Geschichten und Gestalten \/ Allerh <mark>Leute<\/mark> \/ Dorfsünden \/ ","fid":"lange-liste"},{"form":"Leute","weight":"1","pos":7641,"context":" Peter Rosegger: Allerhand <mark>Leute<\/mark>. Wien 1888. ","fid":"lange-liste"},{"form":"Leute","weight":"1","pos":15663,"context":" Thomas Bailey Aldrich: Prudence Palfrey und andere <mark>Leute<\/mark>. Übersetzt von M. Busch. Leipzig 1874....","fid":"lange-liste"},{"form":"Leute","weight":"1","pos":18171,"context":" Elsberg ... Gefährliche <mark>Leute<\/mark>","fid":"lange-liste"},{"form":"Leute","weight":"1","pos":18175,"context":" Kristian Elster: Gefährliche <mark>Leute<\/mark>. Ein socialer Roman. Übersetzt von J. C....","fid":"lange-liste"},{"form":"Leute","weight":"1","pos":20207,"context":"...Gorki ... Fama \/ Warenko \/ Bilger \/ Verlorene <mark>Leute<\/mark> \/ Aus Langeweile \/","fid":"lange-liste"},{"form":"Leute","weight":"1","pos":20286,"context":"...[?] Maksim Gor’kij, Aleksej Maksimovič Peškov: Verlorene <mark>Leute<\/mark>. In: Ausgewählte Erzählungen. Band 4\/5. Übersetzt von...","fid":"lange-liste"}]}]}