{"stem":"loui","instances":[{"docId":"Aurnhammer_Lektuereliste_2_4","docUri":"Aurnhammer_Lektuereliste_2.4.html","score":27,"contexts":[{"form":"Louis","weight":"1","pos":9050,"context":" Unruh .. Offiziere \/ <mark>Louis<\/mark> Ferdinand \/ Geschlecht \/ Opfergang \/ V. d. Entscheid...","fid":"lange-liste"},{"form":"Louis","weight":"1","pos":9063,"context":" Fritz von Unruh: <mark>Louis<\/mark> Ferdinand, Prinz von Preußen. Ein Drama....","fid":"lange-liste"},{"form":"Louis","weight":"1","pos":10219,"context":" <mark>Louis<\/mark> Petit de Bachaumont: Mémoires secrets pour servir à...","fid":"lange-liste"},{"form":"Louis","weight":"1","pos":11880,"context":" [?] <mark>Louis<\/mark> de Hessem, Auguste Lavallé: ?. In: Chinoiseries...","fid":"lange-liste"},{"form":"Louis","weight":"1","pos":11887,"context":"...Auguste Lavallé: ?. In: Chinoiseries, racontées par <mark>Louis<\/mark> de Hessem. Paris 1890. ","fid":"lange-liste"},{"form":"Louis","weight":"1","pos":11930,"context":" Houssaye 1814 \/ 1815 \/ <mark>Louis<\/mark> XVI \/ ","fid":"lange-liste"},{"form":"Louis","weight":"1","pos":11958,"context":" Arsène Houssaye, Arsène Houssaye: <mark>Louis<\/mark> XVI.. In: Galerie du XVIIIe siècle. La...","fid":"lange-liste"},{"form":"Louis","weight":"1","pos":11964,"context":"...In: Galerie du XVIIIe siècle. La Régence. <mark>Louis<\/mark> XV. Louis XVI. La Révolution. Paris 1848...","fid":"lange-liste"},{"form":"Louis","weight":"1","pos":11965,"context":"...du XVIIIe siècle. La Régence. Louis XV. <mark>Louis<\/mark> XVI. La Révolution. Paris 1848. ","fid":"lange-liste"},{"form":"Louis","weight":"1","pos":12070,"context":" Jean-<mark>Louis<\/mark> Dubut de Laforest: Contes pour les baigneuses....","fid":"lange-liste"},{"form":"Louis","weight":"1","pos":12081,"context":" Jean-<mark>Louis<\/mark> Dubut de Laforest: Le Gaga, mœurs parisiennes...","fid":"lange-liste"},{"form":"Louis","weight":"1","pos":12095,"context":" Alphonse-Marie <mark>Louis<\/mark> Prat de Lamartine: Raphaël, pages de la...","fid":"lange-liste"},{"form":"Louis","weight":"1","pos":12107,"context":" Alphonse-Marie <mark>Louis<\/mark> Prat de Lamartine: Souvenirs, impressions, pensées...","fid":"lange-liste"},{"form":"Louis","weight":"1","pos":12127,"context":"...voyageur. Bruxelles 1835. [oder] Alphonse-Marie <mark>Louis<\/mark> Prat de Lamartine: Souvenirs et portraits. Paris...","fid":"lange-liste"},{"form":"Louis","weight":"1","pos":12283,"context":" <mark>Louis<\/mark> Leroy: Lauriane, comédie en trois actes....","fid":"lange-liste"},{"form":"Louis","weight":"1","pos":12367,"context":" [?] ŸS, Pierre Lou, Pierre <mark>Louis<\/mark>: Aphrodite. Ein antikes Sittenbild. [Ohne Übersetzerangabe...","fid":"lange-liste"},{"form":"Louis","weight":"1","pos":12377,"context":"...Budapest 1897. [[?] ŸS, Pierre Lou, Pierre <mark>Louis<\/mark>: Aphrodite. Mœurs antiques. 1896.] ","fid":"lange-liste"},{"form":"Louis","weight":"1","pos":13075,"context":" Charles-<mark>Louis<\/mark> Philippe: La mère et l’enfant. Paris 1900...","fid":"lange-liste"},{"form":"Louis","weight":"1","pos":13083,"context":" Charles-<mark>Louis<\/mark> Philippe: Bubu de Montparnasse. Paris 1901....","fid":"lange-liste"},{"form":"Louis","weight":"1","pos":13091,"context":" Charles-<mark>Louis<\/mark> Philippe: Croquignole. Übersetzt von W. Südel....","fid":"lange-liste"},{"form":"Louis","weight":"1","pos":13100,"context":"...W. Südel. Berlin 1913. [Charles-<mark>Louis<\/mark> Philippe: Croquignole. 1906.] ","fid":"lange-liste"},{"form":"Louis","weight":"1","pos":13106,"context":" Charles-<mark>Louis<\/mark> Philippe: Dans la petite ville. Paris 1910...","fid":"lange-liste"},{"form":"Louis","weight":"1","pos":13351,"context":"...Übersetzt von A. Förster. Berlin 1869. [mit <mark>Louis<\/mark> LEROY] [Hippolyte François Regnier-Destourbet:...","fid":"lange-liste"},{"form":"Louis","weight":"1","pos":13411,"context":"...en France pendant les premières années du règne de <mark>Louis<\/mark> XIV. 1717.] ","fid":"lange-liste"},{"form":"Louis","weight":"1","pos":14020,"context":" <mark>Louis<\/mark> Ulbach: Herr und Madame Fernel. Übersetzt von...","fid":"lange-liste"},{"form":"Louis","weight":"1","pos":14029,"context":"...Übersetzt von A. Mecklenburg. Berlin 1860. [<mark>Louis<\/mark> Ulbach: M. et Mme Fernel. 1860.]...","fid":"lange-liste"},{"form":"Louis","weight":"1","pos":14039,"context":" [?] Charles Lucien <mark>Louis<\/mark>, Pierre Valdagne: L’amour du prochain. Paris...","fid":"lange-liste"}]}]}