{"stem":"oblomov","instances":[{"docId":"Aurnhammer_Lektuereliste_2_4","docUri":"Aurnhammer_Lektuereliste_2.4.html","score":2,"contexts":[{"form":"Oblomov","weight":"1","pos":20188,"context":" Ivan Aleksandrovič Gončarov: <mark>Oblomov<\/mark>. Ein russisches Lebensbild. Übersetzt von B. Borsky...","fid":"lange-liste"},{"form":"Oblomov","weight":"1","pos":20198,"context":".... Leipzig 1869. [Ivan Aleksandrovič Gončarov: <mark>Oblomov<\/mark>. In: Otecestvennye zapiski. 1859.] ","fid":"lange-liste"}]}]}