{"stem":"peau","instances":[{"docId":"Lektuereliste","docUri":"Lektuereliste.html","score":3,"contexts":[{"form":"Peau","weight":"1","pos":11026,"context":"...\/ Blutrache \/ Mundtot \/ Chabert \/ Honorine \/ <mark>Peau<\/mark> -- Illusion \/ Pysid. den mariage \/ Père...","fid":"page"},{"form":"peau","weight":"1","pos":11163,"context":" Honoré de Balzac: La <mark>peau<\/mark> de chagrin. Paris 1831. ","fid":"page"},{"form":"peau","weight":"1","pos":14644,"context":" Pontaille l’infanterie de la <mark>peau<\/mark> ","fid":"page"}]}]}