{"stem":"realisten","instances":[{"docId":"Lektuereliste","docUri":"Lektuereliste.html","score":3,"contexts":[{"form":"Realisten","weight":"1","pos":8239,"context":"...Lynkeus[?] , Josef Popper[?] : Phantasien eines <mark>Realisten<\/mark>. Dresden, [u. a.] 1899. → Tagebuch...","fid":"page"},{"form":"Realisten","weight":"1","pos":22540,"context":"...... Fr Petersburg \/ G.. \/ Gré Missverständnisse \/ <mark>Realisten<\/mark> \/ Kursistin \/ Lukarow \/","fid":"page"},{"form":"Realisten","weight":"1","pos":22605,"context":" Vladimir Petrovič Meščerskij: Die <mark>Realisten<\/mark> der großen Welt. Übersetzt von F. Lortsch....","fid":"page"}]}]}