{"stem":"rené","instances":[{"docId":"Lektuereliste","docUri":"Lektuereliste.html","score":10,"contexts":[{"form":"René","weight":"1","pos":8927,"context":" <mark>René<\/mark> Schickele: Sommernächte. Gedichte. Straßburg 1902....","fid":"page"},{"form":"René","weight":"1","pos":10278,"context":"...Band 1 (1788–1819).Herausgegeben von <mark>René<\/mark> van Rhyn. München 1913. ","fid":"page"},{"form":"René","weight":"1","pos":10293,"context":"...Band 2 (1819–1852).Herausgegeben von <mark>René<\/mark> van Rhyn. München 1914. → Tagebuch ","fid":"page"},{"form":"René","weight":"1","pos":13044,"context":" Pierre Frondaie[?] , Albert <mark>René<\/mark> Fraudet[?] : Montmartre. Paris 1910. →...","fid":"page"},{"form":"Renée","weight":"1","pos":13192,"context":" Jules de Goncourt, Edmond de Goncourt: <mark>Renée<\/mark> Mauperin. Paris 1864. ","fid":"page"},{"form":"René","weight":"1","pos":13810,"context":" Alain <mark>René<\/mark> Lesage: Der Hinkende Teufel. Übersetzt von R....","fid":"page"},{"form":"René","weight":"1","pos":13820,"context":"...Heyland. Hamburg 1730. → Tagebuch [Alain <mark>René<\/mark> Lesage: Le diable boiteux. 1707.] ","fid":"page"},{"form":"René","weight":"1","pos":13826,"context":" Alain <mark>René<\/mark> Lesage: Le diable boiteux. Amsterdam 1707....","fid":"page"},{"form":"René","weight":"1","pos":13834,"context":" Alain <mark>René<\/mark> Lesage: Der spanische Robinson, oder Sonderbahre Geschichte...","fid":"page"},{"form":"René","weight":"1","pos":13848,"context":"...Übersetzerangabe.] Hamburg 1726. → Tagebuch [Alain <mark>René<\/mark> Lesage: Histoire de Gil Blas de Santillane....","fid":"page"}]}]}