{"stem":"richard","instances":[{"docId":"Aurnhammer_Lektuereliste_2_4","docUri":"Aurnhammer_Lektuereliste_2.4.html","score":27,"contexts":[{"form":"Richard","weight":"1","pos":959,"context":" <mark>Richard<\/mark> Beer-Hofmann: Novellen. Berlin 1893....","fid":"lange-liste"},{"form":"Richard","weight":"1","pos":966,"context":" <mark>Richard<\/mark> Beer-Hofmann: Der Tod Georgs. Berlin...","fid":"lange-liste"},{"form":"Richard","weight":"1","pos":974,"context":" <mark>Richard<\/mark> Beer-Hofmann: Der Graf von Charolais....","fid":"lange-liste"},{"form":"Richard","weight":"1","pos":1126,"context":" <mark>Richard<\/mark> Arnold Bermann: Das Seil. Eine Ehegeschichte....","fid":"lange-liste"},{"form":"Richard","weight":"1","pos":2037,"context":" <mark>Richard<\/mark> Dehmel: Der Mitmensch. Drama. Berlin 1895...","fid":"lange-liste"},{"form":"Richard","weight":"1","pos":2043,"context":" <mark>Richard<\/mark> Dehmel: Gedichte. Berlin 1913. (Gesammelte...","fid":"lange-liste"},{"form":"Richard","weight":"1","pos":2051,"context":" <mark>Richard<\/mark> Dehmel: Zwischen Volk und Menschheit. Kriegstagebuch....","fid":"lange-liste"},{"form":"Richard","weight":"1","pos":3623,"context":" <mark>Richard<\/mark> Guttmann: Der Anfänger. Acht Bilder. Berlin...","fid":"lange-liste"},{"form":"Richard","weight":"1","pos":4899,"context":"...Jensen: Die Vivisektion, ihre Gegner und Herr <mark>Richard<\/mark> Wagner. Stuttgart 1881. ","fid":"lange-liste"},{"form":"Richard","weight":"1","pos":5778,"context":" [?] <mark>Richard<\/mark> Leander, Richard von Volkmann: Träumereien an französischen...","fid":"lange-liste"},{"form":"Richard","weight":"1","pos":5780,"context":" [?] Richard Leander, <mark>Richard<\/mark> von Volkmann: Träumereien an französischen Kaminen. Märchen...","fid":"lange-liste"},{"form":"Richard","weight":"1","pos":7712,"context":"   Moritz Gottlieb Saphir (1795 – 1858)   <mark>Richard<\/mark> Saphir (*1892)   ","fid":"lange-liste"},{"form":"Richard","weight":"1","pos":8297,"context":" <mark>Richard<\/mark> Smekal: Das alte Burgtheater. Wien 1916....","fid":"lange-liste"},{"form":"Richard","weight":"1","pos":9195,"context":" <mark>Richard<\/mark> Voss: Novellen. Berlin 1889. ","fid":"lange-liste"},{"form":"Richard","weight":"1","pos":9200,"context":" <mark>Richard<\/mark> Voss: Die neue Circe. Eine italienische Dorfgeschichte...","fid":"lange-liste"},{"form":"Richard","weight":"1","pos":9207,"context":" <mark>Richard<\/mark> Voss: Maria Botti. Novelle. Leipzig 1883...","fid":"lange-liste"},{"form":"Richard","weight":"1","pos":9214,"context":" <mark>Richard<\/mark> Voss: Die Auferstandenen. Antinihilistischer Roman. Dresden...","fid":"lange-liste"},{"form":"Richard","weight":"1","pos":9221,"context":" <mark>Richard<\/mark> Voss: Der Zugvogel. Schauspiel. Leipzig 1893...","fid":"lange-liste"},{"form":"Richard","weight":"1","pos":9231,"context":" [?] Max Waldau, <mark>Richard<\/mark> Georg Spiller von Hauenschild: Nach der Natur....","fid":"lange-liste"},{"form":"Richard","weight":"1","pos":9337,"context":" <mark>Richard<\/mark> Wengraf: Spielzeug. Geschichten. Wien 1912....","fid":"lange-liste"},{"form":"Richard","weight":"1","pos":12294,"context":" <mark>Richard<\/mark> Lesclide: La femme impossible. Paris 1883....","fid":"lange-liste"},{"form":"Richard","weight":"1","pos":12861,"context":" [?] <mark>Richard<\/mark> O’ Monroy, Richard de Saint-Geniès:...","fid":"lange-liste"},{"form":"Richard","weight":"1","pos":12863,"context":" [?] Richard O’ Monroy, <mark>Richard<\/mark> de Saint-Geniès: Le péché Capital....","fid":"lange-liste"},{"form":"Richard","weight":"1","pos":12871,"context":" [?] <mark>Richard<\/mark> O’ Monroy, Richard de Saint-Geniès:...","fid":"lange-liste"},{"form":"Richard","weight":"1","pos":12873,"context":" [?] Richard O’ Monroy, <mark>Richard<\/mark> de Saint-Geniès: Souvent Homme varie!....","fid":"lange-liste"},{"form":"Richard","weight":"1","pos":15946,"context":"...oder die Begegnisse eines Weltmannes. Übersetzt von C. <mark>Richard<\/mark>. Aachen 1833. [Edward George Bulwer-...","fid":"lange-liste"},{"form":"Richard","weight":"1","pos":16842,"context":" <mark>Richard<\/mark> Brinsley Sheridan (1751 – 1816)","fid":"lange-liste"}]}]}