{"stem":"tale","instances":[{"docId":"Aurnhammer_Lektuereliste_2_4","docUri":"Aurnhammer_Lektuereliste_2.4.html","score":6,"contexts":[{"form":"tale","weight":"1","pos":15882,"context":"...1859–1860. [Charles Dickens: A <mark>tale<\/mark> of two cities. 1859.] ","fid":"lange-liste"},{"form":"Tales","weight":"1","pos":16105,"context":"...Egerton, Mary Chavelita Dunne Bright: Discords. <mark>Tales<\/mark>. 1894.] ","fid":"lange-liste"},{"form":"tales","weight":"1","pos":16350,"context":".... Leipzig 1895. [Rudyard Kipling: Plain <mark>tales<\/mark> from the hills. 1890.] ","fid":"lange-liste"},{"form":"Tales","weight":"1","pos":16689,"context":"...Falck. Wien 1900. [Arthur Morrison: <mark>Tales<\/mark> of mean streets. 1894.] ","fid":"lange-liste"},{"form":"Tales","weight":"1","pos":17974,"context":"...Boyesen: The story of an outcast. In: <mark>Tales<\/mark> from two hemispheres. 1877.] ","fid":"lange-liste"},{"form":"Tales","weight":"1","pos":18000,"context":"...: The man who lost his name. In: <mark>Tales<\/mark> from two hemispheres . In: . 1877.] ","fid":"lange-liste"}]}]}