{"stem":"tirso","instances":[{"docId":"Aurnhammer_Lektuereliste_2_4","docUri":"Aurnhammer_Lektuereliste_2.4.html","score":4,"contexts":[{"form":"Tirso","weight":"1","pos":15557,"context":" [?] Fray Gabriel Téllez, <mark>Tirso<\/mark> De Molina: Don Juan, der Wüstling....","fid":"lange-liste"},{"form":"Tirso","weight":"1","pos":15569,"context":".... Penig 1805. [[?] Fray Gabriel Téllez, <mark>Tirso<\/mark> De Molina: El Burlador de Sevilla y convidado...","fid":"lange-liste"},{"form":"Tirso","weight":"1","pos":15579,"context":" [?] Fray Gabriel Téllez, <mark>Tirso<\/mark> De Molina: Die fromme Marta. Übersetzt von...","fid":"lange-liste"},{"form":"Tirso","weight":"1","pos":15590,"context":".... Hildburghausen 1870. [[?] Fray Gabriel Téllez, <mark>Tirso<\/mark> De Molina: Marta la piadosa. 1636.]...","fid":"lange-liste"}]}]}