{"stem":"wunderlichkeiten","instances":[{"docId":"Aurnhammer_Lektuereliste_2_4","docUri":"Aurnhammer_Lektuereliste_2.4.html","score":2,"contexts":[{"form":"Wunderlichkeiten","weight":"1","pos":8848,"context":" Tiek ... Abendgespräche \/ <mark>Wunderlichkeiten<\/mark> \/ Der gest. Kater. \/ Sternbald \/...","fid":"lange-liste"},{"form":"Wunderlichkeiten","weight":"1","pos":8861,"context":" Ludwig Tieck: Abendgespräche. <mark>Wunderlichkeiten<\/mark>. Die Glocke von Aragon. Breslau 1839....","fid":"lange-liste"}]}]}