{"stem":"xvi","instances":[{"docId":"Lektuereliste","docUri":"Lektuereliste.html","score":3,"contexts":[{"form":"XVI","weight":"1","pos":13222,"context":" Houssaye 1814 \/ 1815 \/ Louis <mark>XVI<\/mark> \/ ","fid":"page"},{"form":"XVI","weight":"1","pos":13252,"context":" Arsène Houssaye, Arsène Houssaye: Louis <mark>XVI<\/mark>.. In: Galerie du XVIIIe siècle. La Régence...","fid":"page"},{"form":"XVI","weight":"1","pos":13259,"context":"...XVIIIe siècle. La Régence. Louis XV. Louis <mark>XVI<\/mark>. La Révolution. Paris 1848. → Tagebuch...","fid":"page"}]}]}