{"stem":"yacht","instances":[{"docId":"Lektuereliste","docUri":"Lektuereliste.html","score":3,"contexts":[{"form":"Yacht","weight":"1","pos":21041,"context":" Rung ... Weiße <mark>Yacht<\/mark> ","fid":"page"},{"form":"Yacht","weight":"1","pos":21045,"context":" Otto Rung: Die weiße <mark>Yacht<\/mark>. Übersetzt von E. Stein. Frankfurt am Main...","fid":"page"},{"form":"yacht","weight":"1","pos":21054,"context":"...Main 1911. [Otto Rung: Den hvide <mark>yacht<\/mark>. 1906.] ","fid":"page"}]}]}